{
    "logo" : {
        "source": "images/p.png",
        "height" : 45,
        "width" : 50
    },
    "sections": [
        {
            "title": "Home",
            "href": "/"
        },
        {
            "title": "About",
            "href": "/about"
        },
        {
            "title": "Skills",
            "href": "/skills"
        },
        {
            "title": "Education",
            "href": "/education"
        },
        {
            "title": "Experience",
            "href": "/experience"
        },
        {
            "title": "Projects",
            "href": "/projects"
        },
        {
            "title": "Resume",
            "href": "https://drive.google.com/file/d/1jgd2FU2voSS05BIsP8sNEw2rb1k3ZxDu/view?usp=sharing",
            "type": "link"
        }
    ]

}